{"ai_chatchat.md":"lsuKuTDp","ai_index.md":"B3_5jqnU","database_es_index.md":"DtNXvUf3","database_index.md":"MXOGZ7bg","database_mysql_index.md":"DKNxv9z9","database_mysql_mysql函数以及用法实例.md":"D8TL9wLH","database_mysql_mysql批量插入数据.md":"DUXhA6AE","database_mysql_mysql时间.md":"BmcWOr_s","database_mysql_window-function.md":"DkH_KvEy","database_mysql_windows解压安装.md":"BR846d8F","database_mysql_在线yum安装.md":"EH2qmVPZ","database_oracle_index.md":"Sc6Fo808","database_oracle_oracle表空间.md":"B_MedowO","database_postgresql_analyze.md":"Dq5HLlbs","database_postgresql_index.md":"CVVhSm23","database_postgresql_json.md":"DlMjjbM-","database_postgresql_stat.md":"yzniOhoS","database_redis_index.md":"a2MVufjL","database_redis_redisson.md":"CyZqC3ug","database_redis_redis之ubuntu安装.md":"BrfKQdSY","database_redis_scan 详细.md":"DQ_lzdjx","database_sql-exec-seq.md":"C8hBYL-x","database_sqlserver_index.md":"Ds5EQDHc","database_sqlserver_josn.md":"DAU5VjXj","database_sqlserver_permission.md":"DD2rlQW2","database_sqlserver_systeminfo.md":"DyTzsPBS","index.md":"BXtY3FL7","java_base_collection.md":"BYy1eD8O","java_base_jdk source code make.md":"C74I1SSt","java_base_string support switch.md":"BqnYaKC_","java_concurrent_abstractqueuedsynchronizer.md":"DuJERpB8","java_concurrent_completablefuture.md":"CZ59cpot","java_concurrent_index.md":"Cd9kjeh_","java_concurrent_threadpool.md":"BNJ6kPHb","java_index.md":"xJ_qGUTS","java_jvm_gc.md":"Dm8QenGq","java_jvm_jvm parameter.md":"CawyKtdC","java_jvm_jvm remote.md":"DQ2g32lk","java_jvm_object.md":"Iqxd_w34","java_jvm_synchronized.md":"NnD2uA7i","java_other_bytebuddy.md":"CI1XWNM8","java_other_excel import.md":"BB75NaXm","java_other_jackjson.md":"C7ApehZM","java_other_maven.md":"CukOyIGh","java_other_micrometer.md":"jOisvHsY","java_other_mybatis.md":"CenldCmN","java_other_mybatisplus.md":"M8FZUbdn","java_other_netty.md":"CZsFtrAG","java_other_rocket.md":"Cl-Yk-ro","java_other_shardingsphere.md":"CswQn8WP","java_solve production problems.md":"CBPT8Qbq","java_spring-cloud_context.md":"sG5wAgtD","java_spring-cloud_gateway.md":"D72VQePJ","java_spring-cloud_index.md":"DArueTAW","java_spring-cloud_openfeign.md":"BaHfsdZW","java_spring-cloud_sentinel.md":"yizxDLdE","java_spring_actuator.md":"DUMTrWI_","java_spring_error.md":"DRuvXw1P","java_spring_event.md":"B1TLCZSd","java_spring_gateway.md":"ODo1bVPo","java_spring_index.md":"C68_Sqlq","java_spring_jdbctemplate.md":"BddQQ6lh","java_spring_spring bean接口.md":"BidMiMA2","java_spring_spring ioc.md":"CK1gJCL_","java_spring_spring-aop.md":"DB8TJED1","java_spring_spring-boot启动流程.md":"DH0Z4M-L","java_spring_spring-webflux.md":"BvOY84jM","java_spring_springmvc中获取request.md":"BTnAxoQ4","java_spring_spring扩展接口即执行流程.md":"tSznaLrQ","java_spring_流程图合集.md":"Cim3908u","java_util_arthas.md":"COJ8y4tk","java_util_dateutil.md":"BLK8C-JN","java_util_jdk util.md":"BNiZIF-i","java_util_jmh.md":"BlUXnqhF","ops_docker_easyconnectinit.md":"DWmC3MUJ","ops_docker_index.md":"CnCI_KSi","ops_docker_zabbix.md":"CmgCQZaK","ops_docker_常用命令.md":"BMlotvSP","ops_docker_软件安装_docker阿里云镜像安装.md":"BB4rSxdI","ops_docker_软件安装_rpm离线安装docker.md":"B9KB6oij","ops_docker_软件安装_ubuntu安装docker.md":"CS59PsrG","ops_docker_软件安装_【ubuntu】docker远程连接.md":"9y2hUprb","ops_elasticsearch_index.md":"CCdCtlFA","ops_filebeat_index.md":"B5mGmyfq","ops_grafana_index.md":"kP29xGG8","ops_index.md":"CyKodUpo","ops_jenkins.md":"BV3LK51R","ops_k8s_index.md":"Bz2zs8Jo","ops_k8s_kubectl cheatsheet.md":"CiwyqgUV","ops_k8s_kubectl.md":"Br7b8sMr","ops_logstash_index.md":"Bkl4gH9m","ops_nginx_index.md":"Dv0HqoLj","ops_nginx_nginx 性能参数调优.md":"CCL44Gs0","ops_nginx_nginx-https.md":"DrNCJpNg","ops_nginx_nginx安装.md":"DjosEiQf","ops_nginx_nginx配置.md":"CMlmnyvo","ops_prometheus_alertmanager.md":"B05z4doh","ops_prometheus_index.md":"BEEMEBa6","ops_prometheus_kube-prometheus.md":"vyizT2HE","ops_prometheus_prometheus-operator.md":"DWzrLSfQ","ops_prometheus_query.md":"QFHaOVSi","ops_skywalking_client-config.md":"0BfDQVUz","ops_skywalking_index.md":"DPUgwcGv","ops_skywalking_server-config.md":"ChV0Zjki","ops_skywalking_source-code.md":"Cz6fLYGj","ops_skywalking_ui.md":"DT56WFgz","ops_supervisord.md":"trQ2hLYU","os_index.md":"a6xkPNot","os_linux_alpine.md":"_H-G7HyT","os_linux_centos.md":"D5ZkiJpj","os_linux_index.md":"BOQBh0mm","os_linux_ubuntu.md":"Dd6Jy3wd","os_linux_其他命令.md":"BAmGCqnJ","os_linux_性能分析.md":"BxACHEoN","os_linux_文本分析.md":"Cg1doOXi","os_mac_homebrew.md":"BUz9c6iq","os_mac_index.md":"B2qxoxCt","os_mac_zsh.md":"CQ9iTiJD","os_mac_环境搭建.md":"C_J3CdQ9","os_windows_base64.md":"CpwFZnR8","os_windows_index.md":"DiRSzVTv","os_windows_winserver.md":"CkyNl8Qf","os_windows_wsl.md":"tFRbLTOb","os_windows_乱七八糟.md":"CANQL0yB","os_windows_删除服务.md":"9KUEwSEh","other_algorithm_binarysearch.md":"BabZGwYA","other_algorithm_bit.md":"DuDYr-Qg","other_algorithm_index.md":"lc_HbUjC","other_algorithm_常见算法.md":"BhPfpQyp","other_algorithm_排列组合.md":"Bdjeb6H4","other_http content-type（内容类型）整理.md":"CBqpGYkw","other_hugging-face.md":"Dk-Ih_f1","other_idea相关.md":"DYnHz6X_","other_index.md":"BzaMZoVi","other_travis自动持续集成.md":"D9WqWx82","other_yaml.md":"DeFJuyjk","other_乱七八糟_jquery各种操作.md":"DzuIQNjZ","other_乱七八糟_正则表达式.md":"DMZIo25A","other_收藏转_二分查找法模板.md":"D0QSvr_Q","util_excel.md":"Dfw9O7lv","util_freemarker.md":"BldpxzWR","util_git_config.md":"YLF2hhZm","util_git_count.md":"BCt1lipV","util_git_git-operation.md":"BxaXOhpo","util_git_git-proxy.md":"BksRvBfS","util_git_index.md":"B93Qc3SZ","util_gradle_gradle-task.md":"CepioffY","util_gradle_index.md":"Di6_RVcJ","util_index.md":"DTl5oKZg","util_openwrt.md":"DknNELtX","util_postman-pre-request.md":"DaylODWf","util_ppt.md":"DFWrfc6V","util_privoxy.md":"E2DaiLCW","util_python.md":"Bf9T4yKP","util_unit-test_index.md":"BwvGKon2","util_unit-test_junit.md":"C5iN6NTB","util_unit-test_mockito.md":"XZYNussK"}
